pshield/__init__.py
pshield/pshield.py
pshield/test_pshield.py
pshield-1.0.0.dist-info/METADATA
pshield-1.0.0.dist-info/WHEEL
pshield-1.0.0.dist-info/licenses/LICENSE
pshield-1.0.0.dist-info/RECORD
