Metadata-Version: 2.4
Name: pshield
Version: 1.0.0
Summary: A library to protect your prompts.
Project-URL: Homepage, https://github.com/adiletbaimyrza/promptshield
Project-URL: Issues, https://github.com/adiletbaimyrza/promptshield/issues
Author-email: Adilet Baimyrza <adiletbaimyrza@gmail.com>
License-Expression: MIT
License-File: LICENSE
Classifier: Operating System :: OS Independent
Classifier: Programming Language :: Python :: 3
Requires-Python: >=3.9
Requires-Dist: deep-translator>=1.11.4
Requires-Dist: langdetect>=1.0.9
Requires-Dist: spacy>=3.7.0
